pyunit_calendar/CTC_.py
pyunit_calendar/LSC.py
pyunit_calendar/SC_.py
pyunit_calendar/__init__.py
pyunit_calendar/batchcalendar.py
pyunit_calendar/config.py
pyunit_calendar/date.zip
pyunit_calendar-2020.6.2.dist-info/METADATA
pyunit_calendar-2020.6.2.dist-info/WHEEL
pyunit_calendar-2020.6.2.dist-info/top_level.txt
pyunit_calendar-2020.6.2.dist-info/RECORD
