Metadata-Version: 2.1
Name: pyunit-calendar
Version: 2020.6.2
Summary: 常见的日历转换器
Home-page: https://github.com/PyUnit/pyunit-calendar
Author: Jtyoui
Author-email: jtyoui@qq.com
License: MIT Licence
Platform: any
Classifier: Programming Language :: Python :: 3
Classifier: License :: OSI Approved :: MIT License
Classifier: Operating System :: OS Independent
